bioimageio/spec/__init__.py
bioimageio/spec/_description.py
bioimageio/spec/_description_impl.py
bioimageio/spec/_get_conda_env.py
bioimageio/spec/_io.py
bioimageio/spec/_package.py
bioimageio/spec/_pretty_validation_errors.py
bioimageio/spec/_upload.py
bioimageio/spec/_version.py
bioimageio/spec/common.py
bioimageio/spec/conda_env.py
bioimageio/spec/py.typed
bioimageio/spec/summary.py
bioimageio/spec/utils.py
bioimageio/spec/_internal/__init__.py
bioimageio/spec/_internal/_generated_spdx_license_literals.py
bioimageio/spec/_internal/_settings.py
bioimageio/spec/_internal/common_nodes.py
bioimageio/spec/_internal/constants.py
bioimageio/spec/_internal/field_validation.py
bioimageio/spec/_internal/field_warning.py
bioimageio/spec/_internal/gh_utils.py
bioimageio/spec/_internal/io.py
bioimageio/spec/_internal/io_basics.py
bioimageio/spec/_internal/io_packaging.py
bioimageio/spec/_internal/io_utils.py
bioimageio/spec/_internal/json_schema.py
bioimageio/spec/_internal/license_id.py
bioimageio/spec/_internal/node.py
bioimageio/spec/_internal/node_converter.py
bioimageio/spec/_internal/packaging_context.py
bioimageio/spec/_internal/progress.py
bioimageio/spec/_internal/root_url.py
bioimageio/spec/_internal/type_guards.py
bioimageio/spec/_internal/types.py
bioimageio/spec/_internal/url.py
bioimageio/spec/_internal/utils.py
bioimageio/spec/_internal/validated_string.py
bioimageio/spec/_internal/validated_string_with_inner_node.py
bioimageio/spec/_internal/validation_context.py
bioimageio/spec/_internal/validator_annotations.py
bioimageio/spec/_internal/version_type.py
bioimageio/spec/_internal/warning_levels.py
bioimageio/spec/application/__init__.py
bioimageio/spec/application/v0_2.py
bioimageio/spec/application/v0_3.py
bioimageio/spec/dataset/__init__.py
bioimageio/spec/dataset/v0_2.py
bioimageio/spec/dataset/v0_3.py
bioimageio/spec/generic/__init__.py
bioimageio/spec/generic/_v0_2_converter.py
bioimageio/spec/generic/_v0_3_converter.py
bioimageio/spec/generic/v0_2.py
bioimageio_spec-0.5.7.0.dist-info/licenses/LICENSE
bioimageio_spec-0.5.7.0.dist-info/METADATA
bioimageio_spec-0.5.7.0.dist-info/WHEEL
bioimageio_spec-0.5.7.0.dist-info/top_level.txt
bioimageio_spec-0.5.7.0.dist-info/RECORD
