Metadata-Version: 2.4
Name: bioimageio.spec
Version: 0.5.7.0
Summary: Parser and validator library for bioimage.io specifications
Author-email: Fynn Beuttenmüller <thefynnbe@gmail.com>
Classifier: Development Status :: 3 - Alpha
Classifier: Intended Audience :: Developers
Classifier: Intended Audience :: Science/Research
Classifier: Programming Language :: Python :: 3.8
Classifier: Programming Language :: Python :: 3.9
Classifier: Programming Language :: Python :: 3.10
Classifier: Programming Language :: Python :: 3.11
Classifier: Programming Language :: Python :: 3.12
Classifier: Programming Language :: Python :: 3.13
Requires-Python: >=3.8
License-File: LICENSE
Requires-Dist: annotated-types<1,>=0.5.0
Requires-Dist: email_validator
Requires-Dist: exceptiongroup
Requires-Dist: genericache==0.5.2
Requires-Dist: httpx
Requires-Dist: imageio
Requires-Dist: loguru
Requires-Dist: markdown
Requires-Dist: numpy>=1.21
Requires-Dist: packaging>=17.0
Requires-Dist: platformdirs
Requires-Dist: pydantic-core
Requires-Dist: pydantic-settings<3,>=2.5
Requires-Dist: pydantic<3,>=2.10.3
Requires-Dist: python-dateutil
Requires-Dist: rich
Requires-Dist: ruyaml
Requires-Dist: tifffile>=2020.7.4
Requires-Dist: tqdm
Requires-Dist: typing-extensions
Requires-Dist: zipp
Provides-Extra: dev
Requires-Dist: deepdiff; extra == "dev"
Requires-Dist: devtools; extra == "dev"
Requires-Dist: griffe-pydantic; extra == "dev"
Requires-Dist: griffe-inherited-docstrings; extra == "dev"
Requires-Dist: griffe-public-redundant-aliases; extra == "dev"
Requires-Dist: json_schema_for_humans; extra == "dev"
Requires-Dist: jsonschema; extra == "dev"
Requires-Dist: jupyter; extra == "dev"
Requires-Dist: lxml; extra == "dev"
Requires-Dist: matplotlib; extra == "dev"
Requires-Dist: nbval; extra == "dev"
Requires-Dist: pdoc; extra == "dev"
Requires-Dist: pre-commit; extra == "dev"
Requires-Dist: pyright==1.1.407; extra == "dev"
Requires-Dist: pytest-cov; extra == "dev"
Requires-Dist: pytest; extra == "dev"
Requires-Dist: python-dotenv; extra == "dev"
Requires-Dist: respx; extra == "dev"
Requires-Dist: ruff; extra == "dev"
Requires-Dist: torch; extra == "dev"
Provides-Extra: docs
Requires-Dist: markdown-callouts; extra == "docs"
Requires-Dist: markdown-exec; extra == "docs"
Requires-Dist: markdown-pycon; extra == "docs"
Requires-Dist: mike; extra == "docs"
Requires-Dist: mkdocs-api-autonav; extra == "docs"
Requires-Dist: mkdocs-coverage; extra == "docs"
Requires-Dist: mkdocs-material; extra == "docs"
Requires-Dist: mkdocs-section-index; extra == "docs"
Dynamic: license-file
